makepie/Caches.py
makepie/Config.py
makepie/Decorators.py
makepie/Env.py
makepie/Environement.py
makepie/Exceptions.py
makepie/Macro.py
makepie/Makepie.py
makepie/MakepieLogging.py
makepie/ShellCmd.py
makepie/Utils.py
makepie/Version.py
makepie/__init__.py
makepie/__main__.py
makepie-0.1.50.dist-info/METADATA
makepie-0.1.50.dist-info/WHEEL
makepie-0.1.50.dist-info/entry_points.txt
makepie-0.1.50.dist-info/top_level.txt
makepie-0.1.50.dist-info/RECORD
