Metadata-Version: 2.1
Name: makepie
Version: 0.1.50
Summary: An attempt to replace/improve GNU/make with a python package
Author: Titouan Lacombe
Project-URL: Homepage, https://github.com/titouanlacombe/makepie
Project-URL: Bug Tracker, https://github.com/titouanlacombe/makepie/issues
Project-URL: Documentation, https://github.com/titouanlacombe/makepie/blob/main/README.md
Classifier: Programming Language :: Python :: 3
Classifier: License :: OSI Approved :: MIT License
Classifier: Operating System :: OS Independent
Requires-Python: >=3.7
Requires-Dist: PyYAML (>=5.0)
